License.txt
README.md
setup.cfg
setup.py
Topsis_Jasween_102017187.egg-info/PKG-INFO
Topsis_Jasween_102017187.egg-info/SOURCES.txt
Topsis_Jasween_102017187.egg-info/dependency_links.txt
Topsis_Jasween_102017187.egg-info/requires.txt
Topsis_Jasween_102017187.egg-info/top_level.txt
topsis/__init__.py
topsis/topsis.py