Metadata-Version: 2.1
Name: Topsis-Jasween-102017187
Version: 0.4
Summary: Topsis-Jasween-102017187 is a Python library to solve Multiple Criteria Decision Making(MCDM) problems by using TOPSIS
Home-page: https://github.com/JasweenBrar/Topsis-Jasween-102017187
Author: Jasween Kaur Brar
Author-email: jbrar_be20@thapar.edu
License: MIT
Platform: UNKNOWN
Classifier: Development Status :: 3 - Alpha
Classifier: Intended Audience :: Developers
Classifier: License :: OSI Approved :: MIT License
Classifier: Programming Language :: Python :: 3
Classifier: Programming Language :: Python :: 3.4
Classifier: Programming Language :: Python :: 3.5
Classifier: Programming Language :: Python :: 3.6
Classifier: Programming Language :: Python :: 3.7
Classifier: Programming Language :: Python :: 3.8
License-File: License.txt
